<?xml version="1.0"?>
<pagescount>
	<html_total>8</html_total>
	<html_done>5</html_done>
	<images>15</images>
	<script>10</script>
	<css>10</css>
	<pdf/>
	<documents/>
	<excel/>
	<powerpoint/>
	<flash/>
	<audios/>
	<videos/>
	<xml/>
	<json/>
	<txt/>
	<autocad/>
	<fonts>8</fonts>
	<scraping_reload>1</scraping_reload>
	<is_pretty_url>false</is_pretty_url>
	<is_ebn>false</is_ebn>
	<email>teerachanon6644@gmail.com</email>
	<theme_name>WmdTheme802462</theme_name>
	<server_url_front_page>https://www6.waybackmachinedownloader.com/wdo/files/demo/nmwit.ac.th_teerachanon6644_gmail.com_6t12v293t1/</server_url_front_page>
	<no_www_url>nmwit.ac.th</no_www_url>
	<hosted_domain/>
	<original_archive_url>https://www.nmwit.ac.th/elections/</original_archive_url>
	<final_archive_url>https://www.nmwit.ac.th/elections/</final_archive_url>
	<front_page_code_date/>
	<total_urls_from_api/>
	<max_reached_live>false</max_reached_live>
	<scrape_other_captures>false</scrape_other_captures>
	<total_size>4092</total_size>
</pagescount>
